{
    "sourceFile": "package.json",
    "activeCommit": 0,
    "commits": [
        {
            "activePatchIndex": 1,
            "patches": [
                {
                    "date": 1758505282546,
                    "content": "Index: \n===================================================================\n--- \n+++ \n"
                },
                {
                    "date": 1758893414191,
                    "content": "Index: \n===================================================================\n--- \n+++ \n@@ -1,42 +1,42 @@\n-{\n-  \"name\": \"agendatrampo\",\n-  \"version\": \"1.0.0\",\n-  \"main\": \"index.js\",\n-  \"scripts\": {\n-    \"start\": \"expo start\",\n-    \"android\": \"expo start --android\",\n-    \"ios\": \"expo start --ios\",\n-    \"web\": \"expo start --web\"\n-  },\n-  \"dependencies\": {\n-    \"@expo-google-fonts/amatic-sc\": \"^0.4.1\",\n-    \"@expo-google-fonts/caveat\": \"^0.4.1\",\n-    \"@expo/vector-icons\": \"^14.1.0\",\n-    \"@react-native-async-storage/async-storage\": \"^1.24.0\",\n-    \"@react-native-community/datetimepicker\": \"8.4.1\",\n-    \"@react-native-community/masked-view\": \"^0.1.11\",\n-    \"@react-navigation/drawer\": \"^7.5.8\",\n-    \"@react-navigation/native-stack\": \"^7.3.25\",\n-    \"@react-navigation/stack\": \"^7.4.8\",\n-    \"axios\": \"^1.11.0\",\n-    \"expo\": \"~53.0.22\",\n-    \"expo-font\": \"~13.3.2\",\n-    \"expo-splash-screen\": \"~0.30.10\",\n-    \"expo-status-bar\": \"~2.2.3\",\n-    \"firebase\": \"^12.2.1\",\n-    \"lodash\": \"^4.17.21\",\n-    \"react\": \"19.0.0\",\n-    \"react-native\": \"0.79.6\",\n-    \"react-native-calendars\": \"^1.1313.0\",\n-    \"react-native-dotenv\": \"^3.4.11\",\n-    \"react-native-gesture-handler\": \"~2.24.0\",\n-    \"react-native-reanimated\": \"~3.17.4\",\n-    \"react-native-safe-area-context\": \"5.4.0\",\n-    \"react-native-screens\": \"~4.11.1\",\n-    \"expo-dev-client\": \"~5.2.4\"\n-  },\n-  \"devDependencies\": {\n-    \"@babel/core\": \"^7.20.0\"\n-  },\n-  \"private\": true\n-}\n+{\r\n+  \"name\": \"agendatrampo\",\r\n+  \"version\": \"1.0.0\",\r\n+  \"main\": \"index.js\",\r\n+  \"scripts\": {\r\n+    \"start\": \"expo start\",\r\n+    \"android\": \"expo run:android\",\r\n+    \"ios\": \"expo run:ios\",\r\n+    \"web\": \"expo start --web\"\r\n+  },\r\n+  \"dependencies\": {\r\n+    \"@expo-google-fonts/amatic-sc\": \"^0.4.1\",\r\n+    \"@expo-google-fonts/caveat\": \"^0.4.1\",\r\n+    \"@expo/vector-icons\": \"^14.1.0\",\r\n+    \"@react-native-async-storage/async-storage\": \"^1.24.0\",\r\n+    \"@react-native-community/datetimepicker\": \"8.4.1\",\r\n+    \"@react-native-community/masked-view\": \"^0.1.11\",\r\n+    \"@react-navigation/drawer\": \"^7.5.8\",\r\n+    \"@react-navigation/native-stack\": \"^7.3.25\",\r\n+    \"@react-navigation/stack\": \"^7.4.8\",\r\n+    \"axios\": \"^1.11.0\",\r\n+    \"expo\": \"~53.0.22\",\r\n+    \"expo-dev-client\": \"~5.2.4\",\r\n+    \"expo-font\": \"~13.3.2\",\r\n+    \"expo-splash-screen\": \"~0.30.10\",\r\n+    \"expo-status-bar\": \"~2.2.3\",\r\n+    \"firebase\": \"^12.2.1\",\r\n+    \"lodash\": \"^4.17.21\",\r\n+    \"react\": \"19.0.0\",\r\n+    \"react-native\": \"0.79.6\",\r\n+    \"react-native-calendars\": \"^1.1313.0\",\r\n+    \"react-native-dotenv\": \"^3.4.11\",\r\n+    \"react-native-gesture-handler\": \"~2.24.0\",\r\n+    \"react-native-reanimated\": \"~3.17.4\",\r\n+    \"react-native-safe-area-context\": \"5.4.0\",\r\n+    \"react-native-screens\": \"~4.11.1\"\r\n+  },\r\n+  \"devDependencies\": {\r\n+    \"@babel/core\": \"^7.20.0\"\r\n+  },\r\n+  \"private\": true\r\n+}\r\n"
                }
            ],
            "date": 1758505282546,
            "name": "Commit-0",
            "content": "{\n  \"name\": \"agendatrampo\",\n  \"version\": \"1.0.0\",\n  \"main\": \"index.js\",\n  \"scripts\": {\n    \"start\": \"expo start\",\n    \"android\": \"expo start --android\",\n    \"ios\": \"expo start --ios\",\n    \"web\": \"expo start --web\"\n  },\n  \"dependencies\": {\n    \"@expo-google-fonts/amatic-sc\": \"^0.4.1\",\n    \"@expo-google-fonts/caveat\": \"^0.4.1\",\n    \"@expo/vector-icons\": \"^14.1.0\",\n    \"@react-native-async-storage/async-storage\": \"^1.24.0\",\n    \"@react-native-community/datetimepicker\": \"8.4.1\",\n    \"@react-native-community/masked-view\": \"^0.1.11\",\n    \"@react-navigation/drawer\": \"^7.5.8\",\n    \"@react-navigation/native-stack\": \"^7.3.25\",\n    \"@react-navigation/stack\": \"^7.4.8\",\n    \"axios\": \"^1.11.0\",\n    \"expo\": \"~53.0.22\",\n    \"expo-font\": \"~13.3.2\",\n    \"expo-splash-screen\": \"~0.30.10\",\n    \"expo-status-bar\": \"~2.2.3\",\n    \"firebase\": \"^12.2.1\",\n    \"lodash\": \"^4.17.21\",\n    \"react\": \"19.0.0\",\n    \"react-native\": \"0.79.6\",\n    \"react-native-calendars\": \"^1.1313.0\",\n    \"react-native-dotenv\": \"^3.4.11\",\n    \"react-native-gesture-handler\": \"~2.24.0\",\n    \"react-native-reanimated\": \"~3.17.4\",\n    \"react-native-safe-area-context\": \"5.4.0\",\n    \"react-native-screens\": \"~4.11.1\",\n    \"expo-dev-client\": \"~5.2.4\"\n  },\n  \"devDependencies\": {\n    \"@babel/core\": \"^7.20.0\"\n  },\n  \"private\": true\n}\n"
        }
    ]
}